findJobs/FindJobs.py
findJobs/__init__.py
findJobs/app.py
findJobs/url.py
findJobs/static/drake.png
findJobs/static/styles.css
findJobs/static/temp/salary_boxplot.png
findJobs/static/temp/salary_density.png
findJobs/templates/index.html
FindJobsTW-1.0.7.dist-info/LICENSE
FindJobsTW-1.0.7.dist-info/METADATA
FindJobsTW-1.0.7.dist-info/WHEEL
FindJobsTW-1.0.7.dist-info/top_level.txt
FindJobsTW-1.0.7.dist-info/RECORD
