Metadata-Version: 2.1
Name: FindJobsTW
Version: 1.0.7
Summary: A Python package to find jobs on 104.com.tw based on specific keywords.
Home-page: https://github.com/DannyFin/FindJobsTW
Author: Danny Fin
Author-email: dannyfinselect@outlook.com
Classifier: Programming Language :: Python :: 3
Classifier: License :: OSI Approved :: MIT License
Classifier: Operating System :: OS Independent
License-File: LICENSE
Requires-Dist: flask
Requires-Dist: pandas
Requires-Dist: matplotlib
Requires-Dist: seaborn
Requires-Dist: scipy
Requires-Dist: requests
Requires-Dist: lxml (==4.9.2)
Requires-Dist: beautifulsoup4 (==4.8.0)
Requires-Dist: openpyxl (==3.1.2)
